MANIFEST.in
README.rst
VERSION
mandrill.py
setup.cfg
setup.py
mandrill_really_maintained.egg-info/PKG-INFO
mandrill_really_maintained.egg-info/SOURCES.txt
mandrill_really_maintained.egg-info/dependency_links.txt
mandrill_really_maintained.egg-info/requires.txt
mandrill_really_maintained.egg-info/top_level.txt
scripts/mandrill
scripts/sendmail.mandrill