Metadata-Version: 1.1
Name: mandrill-really-maintained
Version: 1.2.2
Summary: A really maintained CLI client and Python API library for the Mandrill email as a service platform.
Home-page: https://bitbucket.org/hadrien/mandrill-really-maintained
Author: Mandrill Devs
Author-email: community@mandrill.com
License: Apache-2.0
Keywords: mandrill email api
Platform: UNKNOWN
Classifier: Development Status :: 4 - Beta
Classifier: Environment :: Console
Classifier: Intended Audience :: Developers
Classifier: Intended Audience :: System Administrators
Classifier: License :: OSI Approved :: Apache Software License
Classifier: Topic :: Communications :: Email
